rtl/sram_model.v
module sram_model (
    input clk,
    input we,
    input re,
    input [1:0] addr,
    input [7:0] din,
    output reg [7:0] dout
);

reg [7:0] mem [0:3];

always @(posedge clk) begin
    if (we)
        mem[addr] <= din;

    if (re)
        dout <= mem[addr];
end

endmodule

rtl/sram_32bit_wrapper.v
module sram_32bit_wrapper(
    input  wire        clk,
    input  wire        rst,
    input  wire [3:0]  we_byte,
    input  wire        re,
    input  wire [1:0]  addr,
    input  wire [31:0] din,
    output wire [31:0] dout
);

// byte 0: bit [7:0]
sram_model s0 (
    .clk(clk),
    .we(we_byte[0]),
    .re(re),
    .addr(addr),
    .din(din[7:0]),
    .dout(dout[7:0])
);

// byte 1: bit [15:8]
sram_model s1 (
    .clk(clk),
    .we(we_byte[1]),
    .re(re),
    .addr(addr),
    .din(din[15:8]),
    .dout(dout[15:8])
);

// byte 2: bit [23:16]
sram_model s2 (
    .clk(clk),
    .we(we_byte[2]),
    .re(re),
    .addr(addr),
    .din(din[23:16]),
    .dout(dout[23:16])
);

// byte 3: bit [31:24]
sram_model s3 (
    .clk(clk),
    .we(we_byte[3]),
    .re(re),
    .addr(addr),
    .din(din[31:24]),
    .dout(dout[31:24])
);

endmodule

rtl/picorv32_sram_adapter.v
module picorv32_sram_adapter (
    input  wire        clk,
    input  wire        rstn,

    // Giao tiếp với PicoRV32
    input  wire        mem_valid,
    input  wire        mem_instr,
    output reg         mem_ready,
    input  wire [31:0] mem_addr,
    input  wire [31:0] mem_wdata,
    input  wire [3:0]  mem_wstrb,
    output reg  [31:0] mem_rdata,

    // Giao tiếp với SRAM 32-bit wrapper
    output reg  [3:0]  sram_we_byte,
    output reg         sram_re,
    output reg  [1:0]  sram_addr,
    output reg  [31:0] sram_din,
    input  wire [31:0] sram_dout
);

    reg pending_write;
    reg pending_read_1;
    reg pending_read_2;

    wire is_read;
    wire is_write;

    assign is_read  = mem_valid && (mem_wstrb == 4'b0000);
    assign is_write = mem_valid && (mem_wstrb != 4'b0000);

    always @(posedge clk or negedge rstn) begin
        if (!rstn) begin
            mem_ready      <= 1'b0;
            mem_rdata      <= 32'b0;
            sram_we_byte   <= 4'b0000;
            sram_re        <= 1'b0;
            sram_addr      <= 2'b00;
            sram_din       <= 32'b0;
            pending_write  <= 1'b0;
            pending_read_1 <= 1'b0;
            pending_read_2 <= 1'b0;
        end else begin
            // mặc định
            mem_ready    <= 1'b0;
            sram_we_byte <= 4'b0000;
            sram_re      <= 1'b0;

            // nhận yêu cầu mới khi đang rảnh
            if (!pending_write && !pending_read_1 && !pending_read_2 && mem_valid) begin
                sram_addr <= mem_addr[3:2];
                sram_din  <= mem_wdata;

                if (is_write) begin
                    sram_we_byte  <= mem_wstrb;
                    pending_write <= 1'b1;
                end
                else if (is_read) begin
                    sram_re        <= 1'b1;
                    pending_read_1 <= 1'b1;
                end
            end

            // hoàn tất ghi sau 1 chu kỳ
            else if (pending_write) begin
                mem_ready     <= 1'b1;
                pending_write <= 1'b0;
            end

            // đọc đang chờ chu kỳ thứ 1
            else if (pending_read_1) begin
                pending_read_1 <= 1'b0;
                pending_read_2 <= 1'b1;
            end

            // đọc hoàn tất ở chu kỳ thứ 2
            else if (pending_read_2) begin
                mem_rdata      <= sram_dout;
                mem_ready      <= 1'b1;
                pending_read_2 <= 1'b0;
            end
        end
    end

endmodule

rtl/adapter_sram_top.v
module adapter_sram_top (
    input  wire        clk,
    input  wire        rstn,

    // giao tiếp giả lập phía CPU
    input  wire        mem_valid,
    input  wire        mem_instr,
    output wire        mem_ready,
    input  wire [31:0] mem_addr,
    input  wire [31:0] mem_wdata,
    input  wire [3:0]  mem_wstrb,
    output wire [31:0] mem_rdata
);

    wire [3:0]  sram_we_byte;
    wire        sram_re;
    wire [1:0]  sram_addr;
    wire [31:0] sram_din;
    wire [31:0] sram_dout;

    picorv32_sram_adapter u_adapter (
        .clk(clk),
        .rstn(rstn),

        .mem_valid(mem_valid),
        .mem_instr(mem_instr),
        .mem_ready(mem_ready),
        .mem_addr(mem_addr),
        .mem_wdata(mem_wdata),
        .mem_wstrb(mem_wstrb),
        .mem_rdata(mem_rdata),

        .sram_we_byte(sram_we_byte),
        .sram_re(sram_re),
        .sram_addr(sram_addr),
        .sram_din(sram_din),
        .sram_dout(sram_dout)
    );

    sram_32bit_wrapper u_mem (
        .clk(clk),
        .rst(~rstn),
        .we_byte(sram_we_byte),
        .re(sram_re),
        .addr(sram_addr),
        .din(sram_din),
        .dout(sram_dout)
    );

endmodule

tb/tb_adapter_sram.v
`timescale 1ns/1ps

module tb_adapter_sram;

    reg         clk;
    reg         rstn;

    reg         mem_valid;
    reg         mem_instr;
    wire        mem_ready;
    reg  [31:0] mem_addr;
    reg  [31:0] mem_wdata;
    reg  [3:0]  mem_wstrb;
    wire [31:0] mem_rdata;

    adapter_sram_top dut (
        .clk(clk),
        .rstn(rstn),
        .mem_valid(mem_valid),
        .mem_instr(mem_instr),
        .mem_ready(mem_ready),
        .mem_addr(mem_addr),
        .mem_wdata(mem_wdata),
        .mem_wstrb(mem_wstrb),
        .mem_rdata(mem_rdata)
    );

    // tạo clock 10ns
    initial begin
        clk = 0;
        forever #5 clk = ~clk;
    end

    // task ghi bộ nhớ
    task do_write;
        input [31:0] addr;
        input [31:0] data;
        input [3:0]  wstrb;
        begin
            @(negedge clk);
            mem_valid = 1'b1;
            mem_addr  = addr;
            mem_wdata = data;
            mem_wstrb = wstrb;
            mem_instr = 1'b0;

            @(negedge clk);
            while (mem_ready != 1'b1)
                @(negedge clk);

            @(negedge clk);
            mem_valid = 1'b0;
            mem_addr  = 32'b0;
            mem_wdata = 32'b0;
            mem_wstrb = 4'b0000;
        end
    endtask

    // task đọc bộ nhớ
    task do_read;
        input [31:0] addr;
        begin
            @(negedge clk);
            mem_valid = 1'b1;
            mem_addr  = addr;
            mem_wdata = 32'b0;
            mem_wstrb = 4'b0000;
            mem_instr = 1'b0;

            @(negedge clk);
            while (mem_ready != 1'b1)
                @(negedge clk);

            $display("READ addr=%h data=%h time=%0t", mem_addr, mem_rdata, $time);

            @(negedge clk);
            mem_valid = 1'b0;
            mem_addr  = 32'b0;
            mem_wdata = 32'b0;
            mem_wstrb = 4'b0000;
        end
    endtask

    initial begin
        // dump waveform
        $dumpfile("wave_adapter_sram.vcd");
        $dumpvars(0, tb_adapter_sram);

        // giá trị đầu
        rstn      = 1'b0;
        mem_valid = 1'b0;
        mem_instr = 1'b0;
        mem_addr  = 32'b0;
        mem_wdata = 32'b0;
        mem_wstrb = 4'b0000;

        // reset
        #20;
        rstn = 1'b1;
        #20;

        // test 1: ghi cả word vào word 0
        do_write(32'h0000_0000, 32'h1234_5678, 4'b1111);
        do_read (32'h0000_0000);

        // test 2: chỉ ghi byte thấp nhất tại word 0
        do_write(32'h0000_0000, 32'h0000_00AA, 4'b0001);
        do_read (32'h0000_0000);

        // test 3: ghi word khác ở word 1
        do_write(32'h0000_0004, 32'hDEAD_BEEF, 4'b1111);
        do_read (32'h0000_0004);

        // test 4: chỉ ghi byte cao nhất của word 1
        do_write(32'h0000_0004, 32'h1100_0000, 4'b1000);
        do_read (32'h0000_0004);

        #50;
        $finish;
    end

endmodule

sim/wave_adapter_sram.vcd
$date
	Tue Mar 24 09:34:34 2026
$end
$version
	Icarus Verilog
$end
$timescale
	1ps
$end
$scope module tb_adapter_sram $end
$var wire 1 ! mem_ready $end
$var wire 32 " mem_rdata [31:0] $end
$var reg 1 # clk $end
$var reg 32 $ mem_addr [31:0] $end
$var reg 1 % mem_instr $end
$var reg 1 & mem_valid $end
$var reg 32 ' mem_wdata [31:0] $end
$var reg 4 ( mem_wstrb [3:0] $end
$var reg 1 ) rstn $end
$scope module dut $end
$var wire 1 # clk $end
$var wire 32 * mem_addr [31:0] $end
$var wire 1 % mem_instr $end
$var wire 1 & mem_valid $end
$var wire 32 + mem_wdata [31:0] $end
$var wire 4 , mem_wstrb [3:0] $end
$var wire 1 ) rstn $end
$var wire 4 - sram_we_byte [3:0] $end
$var wire 1 . sram_re $end
$var wire 32 / sram_dout [31:0] $end
$var wire 32 0 sram_din [31:0] $end
$var wire 2 1 sram_addr [1:0] $end
$var wire 1 ! mem_ready $end
$var wire 32 2 mem_rdata [31:0] $end
$scope module u_adapter $end
$var wire 1 # clk $end
$var wire 1 3 is_read $end
$var wire 1 4 is_write $end
$var wire 32 5 mem_addr [31:0] $end
$var wire 1 % mem_instr $end
$var wire 1 & mem_valid $end
$var wire 32 6 mem_wdata [31:0] $end
$var wire 4 7 mem_wstrb [3:0] $end
$var wire 1 ) rstn $end
$var wire 32 8 sram_dout [31:0] $end
$var reg 32 9 mem_rdata [31:0] $end
$var reg 1 ! mem_ready $end
$var reg 1 : pending_read_1 $end
$var reg 1 ; pending_read_2 $end
$var reg 1 < pending_write $end
$var reg 2 = sram_addr [1:0] $end
$var reg 32 > sram_din [31:0] $end
$var reg 1 . sram_re $end
$var reg 4 ? sram_we_byte [3:0] $end
$upscope $end
$scope module u_mem $end
$var wire 2 @ addr [1:0] $end
$var wire 1 # clk $end
$var wire 32 A din [31:0] $end
$var wire 1 . re $end
$var wire 1 B rst $end
$var wire 4 C we_byte [3:0] $end
$var wire 32 D dout [31:0] $end
$scope module s0 $end
$var wire 2 E addr [1:0] $end
$var wire 1 # clk $end
$var wire 8 F din [7:0] $end
$var wire 1 . re $end
$var wire 1 G we $end
$var reg 8 H dout [7:0] $end
$upscope $end
$scope module s1 $end
$var wire 2 I addr [1:0] $end
$var wire 1 # clk $end
$var wire 8 J din [7:0] $end
$var wire 1 . re $end
$var wire 1 K we $end
$var reg 8 L dout [7:0] $end
$upscope $end
$scope module s2 $end
$var wire 2 M addr [1:0] $end
$var wire 1 # clk $end
$var wire 8 N din [7:0] $end
$var wire 1 . re $end
$var wire 1 O we $end
$var reg 8 P dout [7:0] $end
$upscope $end
$scope module s3 $end
$var wire 2 Q addr [1:0] $end
$var wire 1 # clk $end
$var wire 8 R din [7:0] $end
$var wire 1 . re $end
$var wire 1 S we $end
$var reg 8 T dout [7:0] $end
$upscope $end
$upscope $end
$upscope $end
$scope task do_read $end
$var reg 32 U addr [31:0] $end
$upscope $end
$scope task do_write $end
$var reg 32 V addr [31:0] $end
$var reg 32 W data [31:0] $end
$var reg 4 X wstrb [3:0] $end
$upscope $end
$upscope $end
$enddefinitions $end
$comment Show the parameter values. $end
$dumpall
$end
#0
$dumpvars
bx X
bx W
bx V
bx U
bx T
0S
b0 R
b0 Q
bx P
0O
b0 N
b0 M
bx L
0K
b0 J
b0 I
bx H
0G
b0 F
b0 E
bx D
b0 C
1B
b0 A
b0 @
b0 ?
b0 >
b0 =
0<
0;
0:
b0 9
bx 8
b0 7
b0 6
b0 5
04
03
b0 2
b0 1
b0 0
bx /
0.
b0 -
b0 ,
b0 +
b0 *
0)
b0 (
b0 '
0&
0%
b0 $
0#
b0 "
0!
$end
#5000
1#
#10000
0#
#15000
1#
#20000
0B
0#
1)
#25000
1#
#30000
0#
#35000
1#
#40000
14
b1111 (
b1111 ,
b1111 7
b10010001101000101011001111000 '
b10010001101000101011001111000 +
b10010001101000101011001111000 6
1&
0#
b1111 X
b10010001101000101011001111000 W
b0 V
#45000
1G
1K
1O
1S
b1111000 F
b1010110 J
b110100 N
b10010 R
1<
b1111 -
b1111 ?
b1111 C
b10010001101000101011001111000 0
b10010001101000101011001111000 >
b10010001101000101011001111000 A
1#
#50000
0#
#55000
0G
0K
0O
0S
0<
1!
b0 -
b0 ?
b0 C
1#
#60000
0#
#65000
1G
1K
1O
1S
1<
b1111 -
b1111 ?
b1111 C
0!
1#
#70000
04
b0 U
b0 (
b0 ,
b0 7
b0 '
b0 +
b0 6
0&
0#
#75000
0G
0K
0O
0S
0<
1!
b0 -
b0 ?
b0 C
1#
#80000
13
1&
0#
#85000
b0 F
b0 J
b0 N
b0 R
1:
1.
b0 0
b0 >
b0 A
0!
1#
#90000
0#
#95000
1;
0:
0.
b10010 T
b110100 P
b1010110 L
b10010001101000101011001111000 /
b10010001101000101011001111000 8
b10010001101000101011001111000 D
b1111000 H
1#
#100000
0#
#105000
0;
1!
b10010001101000101011001111000 "
b10010001101000101011001111000 2
b10010001101000101011001111000 9
1#
#110000
0#
#115000
1:
1.
0!
1#
#120000
03
b1 X
b10101010 W
0&
0#
#125000
1;
0:
0.
1#
#130000
14
b1 (
b1 ,
b1 7
b10101010 '
b10101010 +
b10101010 6
1&
0#
#135000
0;
1!
1#
#140000
0#
#145000
1G
b10101010 F
1<
b1 -
b1 ?
b1 C
b10101010 0
b10101010 >
b10101010 A
0!
1#
#150000
04
b0 (
b0 ,
b0 7
b0 '
b0 +
b0 6
0&
0#
#155000
0G
0<
1!
b0 -
b0 ?
b0 C
1#
#160000
13
1&
0#
#165000
b0 F
1:
1.
b0 0
b0 >
b0 A
0!
1#
#170000
0#
#175000
1;
0:
0.
b10010001101000101011010101010 /
b10010001101000101011010101010 8
b10010001101000101011010101010 D
b10101010 H
1#
#180000
0#
#185000
0;
1!
b10010001101000101011010101010 "
b10010001101000101011010101010 2
b10010001101000101011010101010 9
1#
#190000
0#
#195000
1:
1.
0!
1#
#200000
03
b1111 X
b11011110101011011011111011101111 W
b100 V
0&
0#
#205000
1;
0:
0.
1#
#210000
14
b1111 (
b1111 ,
b1111 7
b11011110101011011011111011101111 '
b11011110101011011011111011101111 +
b11011110101011011011111011101111 6
b100 $
b100 *
b100 5
1&
0#
#215000
0;
1!
1#
#220000
0#
#225000
1G
1K
1O
1S
b11101111 F
b10111110 J
b10101101 N
b11011110 R
1<
b1111 -
b1111 ?
b1111 C
b11011110101011011011111011101111 0
b11011110101011011011111011101111 >
b11011110101011011011111011101111 A
b1 1
b1 =
b1 @
b1 E
b1 I
b1 M
b1 Q
0!
1#
#230000
04
b100 U
b0 (
b0 ,
b0 7
b0 '
b0 +
b0 6
b0 $
b0 *
b0 5
0&
0#
#235000
0G
0K
0O
0S
0<
1!
b0 -
b0 ?
b0 C
1#
#240000
13
b100 $
b100 *
b100 5
1&
0#
#245000
b0 F
b0 J
b0 N
b0 R
1:
1.
b0 0
b0 >
b0 A
0!
1#
#250000
0#
#255000
1;
0:
0.
b11011110 T
b10101101 P
b10111110 L
b11011110101011011011111011101111 /
b11011110101011011011111011101111 8
b11011110101011011011111011101111 D
b11101111 H
1#
#260000
0#
#265000
0;
1!
b11011110101011011011111011101111 "
b11011110101011011011111011101111 2
b11011110101011011011111011101111 9
1#
#270000
0#
#275000
1:
1.
0!
1#
#280000
03
b1000 X
b10001000000000000000000000000 W
b0 $
b0 *
b0 5
0&
0#
#285000
1;
0:
0.
1#
#290000
14
b1000 (
b1000 ,
b1000 7
b10001000000000000000000000000 '
b10001000000000000000000000000 +
b10001000000000000000000000000 6
b100 $
b100 *
b100 5
1&
0#
#295000
0;
1!
1#
#300000
0#
#305000
1S
b10001 R
1<
b1000 -
b1000 ?
b1000 C
b10001000000000000000000000000 0
b10001000000000000000000000000 >
b10001000000000000000000000000 A
0!
1#
#310000
04
b0 (
b0 ,
b0 7
b0 '
b0 +
b0 6
b0 $
b0 *
b0 5
0&
0#
#315000
0S
0<
1!
b0 -
b0 ?
b0 C
1#
#320000
13
b100 $
b100 *
b100 5
1&
0#
#325000
b0 R
1:
1.
b0 0
b0 >
b0 A
0!
1#
#330000
0#
#335000
1;
0:
0.
b10001101011011011111011101111 /
b10001101011011011111011101111 8
b10001101011011011111011101111 D
b10001 T
1#
#340000
0#
#345000
0;
1!
b10001101011011011111011101111 "
b10001101011011011111011101111 2
b10001101011011011111011101111 9
1#
#350000
0#
#355000
1:
1.
0!
1#
#360000
03
b0 $
b0 *
b0 5
0&
0#
#365000
1;
0:
0.
1#
#370000
0#
#375000
0;
1!
1#
#380000
0#
#385000
0!
1#
